{
    "contentVersion": "1.0.0.0",
    "$schema": "http://schema.management.azure.com/schemas/2015-01-01/deploymentTemplate.json#",
    "parameters": {
        "accountName": {
            "type": "string",
            "metadata": {
                "description": "Name of the cosmosdb account"
            }
        },
        "databaseName": {
            "type": "string",
            "metadata": {
                "description": "Name of the database to create on the cosmosdb account"
            }            
        },
        "useSharedRequestUnits": {
            "type": "bool",
            "defaultValue": "false",
            "metadata": {
                "description": "Provisions all the collections to use the shared RU of the database. Database requires at least 100RU per collection"
            }
        },
        "offerThroughput": {
            "type": "int",
            "defaultValue": 400,
            "metadata": {
                "description": "When 'useSharedRequestUnits' is set,  sets the databases Request Units.  The minimum assignment is 100 RUs per collection.  RUs must be assigned in increments of 100."
            }
        },
        "databaseNeedsCreation": {
            "type": "bool",
            "defaultValue": "false",
            "metadata": {
                "description": "Set to true when the database needs creating. Works around ARM limitation."
            }
        }
    },
    "variables": {
        "DefaultDatabaseProperties": {
            "resource":{
                "id": "[parameters('databaseName')]"
            }
        },
        "DatabaseThroughputCreationOption": [
            {
            },
            {
                "options": {
                    "throughput": "[parameters('offerThroughput')]"
                }
            }
        ],
        "DatabasePropertyOption": "[int(if(and(parameters('useSharedRequestUnits'), parameters('databaseNeedsCreation')), 1, 0))]",        
        "DatabaseProperties": "[union(variables('DefaultDatabaseProperties'), variables('DatabaseThroughputCreationOption')[variables('DatabasePropertyOption')])]",
        "VariableExplaination": [ 
            "This variable contains comments about variables",
            
            "DatabasePropertyOption",
            "This variables purpose is to determine which item from the DatabaseThroughputCreationOption variable to use given the parameters passed in.",
            "This is an artifact of the azure resources - creating a cosmos database requires a object called 'options' on the resource properties, ",
            "containing a 'throughput' property,  but it is set via a sub-resource at all other times.",

            "DatabaseProperties",
            "This variable contains the final database creation/update properties used by the template, and uses the DatabasePropertyOption to select the correct throughput options to use."
        ]
    },
    "resources": [
        {
            "type": "Microsoft.DocumentDB/databaseAccounts/apis/databases",
            "name": "[concat(parameters('accountName'), '/sql/', parameters('databaseName'))]",
            "apiVersion": "2016-03-31",
            "properties": "[variables('DatabaseProperties')]"
        },
        {
            "condition": "[parameters('useSharedRequestUnits')]",
            "type": "Microsoft.DocumentDB/databaseAccounts/apis/databases/settings",
            "name": "[concat(parameters('accountName'), '/sql/', parameters('databaseName'), '/throughput')]",
            "apiVersion": "2016-03-31",
            "dependsOn": [ "[resourceId('Microsoft.DocumentDB/databaseAccounts/apis/databases', parameters('accountName'), 'sql', parameters('databaseName'))]" ],
            "properties":{
                "resource":{
                    "throughput": "[parameters('offerThroughput')]"
                }
            }
        }
    ]    
}